<?xml version="1.0" encoding="UTF-8"?>
<Root><Arrays><Array Type="Image" Name="Exp1Cam1" Width="1341" Height="1012" BitsPerPixel="16" CompressionType="" CompressionRate="" Factor="1.000000"/><Array Type="Image" Name="Exp1Cam3" Width="1341" Height="1012" BitsPerPixel="16" CompressionType="" CompressionRate="" Factor="1.000000" Description=""/></Arrays><FLEX version="1.8.1.0" OperaDevice="OPERA3845"><LightSources><LightSource ID="Laser_1" LightSourceType="Laser"><Wavelength Type="integer" Unit="nm">488</Wavelength></LightSource><LightSource ID="Laser_2" LightSourceType="Laser"><Wavelength Type="integer" Unit="nm">561</Wavelength></LightSource><LightSource ID="Laser_3" LightSourceType="Laser"><Wavelength Type="integer" Unit="nm">640</Wavelength></LightSource><LightSource ID="Laser_4" LightSourceType="Laser"><Wavelength Type="integer" Unit="nm">405</Wavelength></LightSource></LightSources><Filters><Slider Name="Camera1"><Filter ID="450/50"/><Filter ID="540/75"/><Filter ID="562/40"/><Filter ID="520/35"/><Filter ID="empty2"/><Filter ID="empty3"/></Slider><Slider Name="Camera2"><Filter ID="565/40"/><Filter ID="585/40"/><Filter ID="600/40"/><Filter ID="540/75"/><Filter ID="empty2"/><Filter ID="empty3"/></Slider><Slider Name="Camera3"><Filter ID="690/70"/></Slider><Slider Name="Detect_Dichro"><Filter ID="510"/><Filter ID="568"/><Filter ID="empty1"/></Slider><Slider Name="Primary_Dichro"><Filter ID="405/488"/><Filter ID="405/488/640"/><Filter ID="405/561/640"/></Slider></Filters><Cameras><Camera ID="Camera_1" CameraType="High QE CCD"><PixelSizeX Type="decimal" Unit="m">6.459e-006</PixelSizeX><PixelSizeY Type="decimal" Unit="m">6.459e-006</PixelSizeY></Camera><Camera ID="Camera_2" CameraType="High QE CCD"><PixelSizeX Type="decimal" Unit="m">6.459e-006</PixelSizeX><PixelSizeY Type="decimal" Unit="m">6.459e-006</PixelSizeY></Camera><Camera ID="Camera_3" CameraType="High QE CCD"><PixelSizeX Type="decimal" Unit="m">6.459e-006</PixelSizeX><PixelSizeY Type="decimal" Unit="m">6.459e-006</PixelSizeY></Camera></Cameras><Objectives><Objective ID="10x_Air_UPlanSApo"><Magnification Type="decimal">10.0</Magnification><NumAperture Type="decimal">0.40</NumAperture><Immersion Type="decimal">1.00</Immersion></Objective><Objective ID="20xW_UAPO20xW3/340_NA=0.7"><Magnification Type="decimal">20.0</Magnification><NumAperture Type="decimal">0.70</NumAperture><Immersion Type="decimal">1.33</Immersion></Objective><Objective ID="20x_Air_LCPLF_NA=0.4"><Magnification Type="decimal">20.0</Magnification><NumAperture Type="decimal">0.40</NumAperture><Immersion Type="decimal">1.00</Immersion></Objective><Objective ID="40xW_PlanAPO_40xWLSM_NA=0.9"><Magnification Type="decimal">40.0</Magnification><NumAperture Type="decimal">0.90</NumAperture><Immersion Type="decimal">1.33</Immersion></Objective></Objectives><Sublayouts><Sublayout ID="SL_Sample"><Field No="1"><OffsetX Type="decimal" Unit="m">0.000e+000</OffsetX><OffsetY Type="decimal" Unit="m">0.000e+000</OffsetY></Field></Sublayout></Sublayouts><Stacks><Stack ID="St_Sample"><Plane No="1"><OffsetZ Type="decimal" Unit="m">0.000e+000</OffsetZ></Plane></Stack></Stacks><Kinetics><Kinetic ID="SK_Sample"/></Kinetics><DispensingSteps><Dispensing ID="Di_Sample"/></DispensingSteps><LightSourceCombinations><LightSourceCombination ID="LS_Sample_1"><LightSourceRef ID="Laser_3"><Power Type="decimal" Unit="W">2.960e-003</Power></LightSourceRef><LightSourceRef ID="Laser_4"><Power Type="decimal" Unit="W">1.190e-003</Power></LightSourceRef></LightSourceCombination></LightSourceCombinations><FilterCombinations><FilterCombination ID="F_Sample_1"><SliderRef ID="Camera1" Filter="450/50"/><SliderRef ID="Camera2" Filter="565/40"/><SliderRef ID="Camera3" Filter="690/70"/><SliderRef ID="Primary_Dichro" Filter="405/488/640"/><SliderRef ID="Detect_Dichro" Filter="510"/></FilterCombination></FilterCombinations><Plate><PlateName Type="string">1536_Aurora_COC_200um</PlateName><XSize Type="integer">32</XSize><YSize Type="integer">48</YSize><WellShape><Shape>rectangle</Shape><XSize Type="decimal" Unit="m">1.451e-003</XSize><YSize Type="decimal" Unit="m">1.407e-003</YSize></WellShape><Barcode Type="string">C7530395</Barcode><StartTime Type="date">2009-03-24T01:18:58</StartTime><OperaMeasNo Type="integer">1</OperaMeasNo></Plate><Well><AreaName>Sample</AreaName><WellCoordinate Row="1" Col="1"/><SublayoutRef>SL_Sample</SublayoutRef><StackRef>St_Sample</StackRef><KineticRef>SK_Sample</KineticRef><DispensingRef>Di_Sample</DispensingRef><Images><Image BufferNo="0"><ObjectiveRef>10x_Air_UPlanSApo</ObjectiveRef><FilterCombinationRef>F_Sample_1</FilterCombinationRef><LightSourceCombinationRef>LS_Sample_1</LightSourceCombinationRef><ExposureNo Type="integer">1</ExposureNo><CameraExposureTime Type="decimal" Unit="s">4.000e-001</CameraExposureTime><CameraBinningX Type="integer">1</CameraBinningX><CameraBinningY Type="integer">1</CameraBinningY><Stack Type="integer">1</Stack><Sublayout Type="integer">1</Sublayout><FocusHeight Type="decimal" Unit="m">0.000e+000</FocusHeight><AbsoluteFocusHeight Type="decimal" Unit="m">2.17508e-002</AbsoluteFocusHeight><AbsolutePiezoHeight Type="decimal" Unit="m">1.249e-004</AbsolutePiezoHeight><RelativeZ Type="decimal" Unit="m">0.000e+000</RelativeZ><PositionX Type="decimal" Unit="m">0.000e+000</PositionX><PositionY Type="decimal" Unit="m">0.000e+000</PositionY><PositionZ Type="decimal" Unit="m">0.000e+000</PositionZ><MeasurementTimeOffset Type="decimal" Unit="s">20.00</MeasurementTimeOffset><DateTime Type="date">2009-03-24T01:19:18</DateTime><CameraRef>Camera_1</CameraRef><ImageType>Signal</ImageType><ImageFactor Type="decimal">1.000000</ImageFactor><ImageBitPerPixel Type="integer">16</ImageBitPerPixel><ImageWidth Type="integer">1341</ImageWidth><ImageHeight Type="integer">1012</ImageHeight><CompressionType Type="string"></CompressionType><CompressionRate Type="decimal"></CompressionRate><ImageResolutionX Type="decimal" Unit="m">6.459e-007</ImageResolutionX><ImageResolutionY Type="decimal" Unit="m">6.459e-007</ImageResolutionY></Image><Image BufferNo="1"><ObjectiveRef>10x_Air_UPlanSApo</ObjectiveRef><FilterCombinationRef>F_Sample_1</FilterCombinationRef><LightSourceCombinationRef>LS_Sample_1</LightSourceCombinationRef><ExposureNo Type="integer">1</ExposureNo><CameraExposureTime Type="decimal" Unit="s">4.000e-001</CameraExposureTime><CameraBinningX Type="integer">1</CameraBinningX><CameraBinningY Type="integer">1</CameraBinningY><Stack Type="integer">1</Stack><Sublayout Type="integer">1</Sublayout><FocusHeight Type="decimal" Unit="m">0.000e+000</FocusHeight><AbsoluteFocusHeight Type="decimal" Unit="m">2.17508e-002</AbsoluteFocusHeight><AbsolutePiezoHeight Type="decimal" Unit="m">1.249e-004</AbsolutePiezoHeight><RelativeZ Type="decimal" Unit="m">0.000e+000</RelativeZ><PositionX Type="decimal" Unit="m">0.000e+000</PositionX><PositionY Type="decimal" Unit="m">0.000e+000</PositionY><PositionZ Type="decimal" Unit="m">0.000e+000</PositionZ><MeasurementTimeOffset Type="decimal" Unit="s">20.00</MeasurementTimeOffset><DateTime Type="date">2009-03-24T01:19:18</DateTime><CameraRef>Camera_3</CameraRef><ImageType>Signal</ImageType><ImageFactor Type="decimal">1.000000</ImageFactor><ImageBitPerPixel Type="integer">16</ImageBitPerPixel><ImageWidth Type="integer">1341</ImageWidth><ImageHeight Type="integer">1012</ImageHeight><CompressionType Type="string"></CompressionType><CompressionRate Type="decimal"></CompressionRate><ImageResolutionX Type="decimal" Unit="m">6.459e-007</ImageResolutionX><ImageResolutionY Type="decimal" Unit="m">6.459e-007</ImageResolutionY></Image></Images></Well></FLEX><StatusReport><Status StatusString="Scripts "/></StatusReport></Root>
